{"skill_id":"developer.pre-flight-check","agent_role":"developer","description":"Advisory self-check in a disposable workspace (typecheck + affected tests) with bounded self-correction; repeated signature or exhausted budget => escalate. Never the verdict.","version":"0.1.0","status":"needs_tests","entry_documents":["SKILL.md"],"scripts":["scripts/evaluate.py"],"tests":["tests/test_skill.py"],"validation":["pytest -q tests/"],"memory_file":".memory.md","depends_on":[],"enhances":["developer.patch-proposal","developer.spec-conformance"],"provenance":{"source_story":"","source_trajectory":"reliability gates","created_by":"harness"},"failure_signatures":["unbounded|self|correct","command|not|allowlisted"],"last_evaluation":{"passed":0,"total":0,"fresh_runs":0,"pass_rate":0.0,"at":""},"leakage_audit":"unrun"}
